relativeImp/__init__.py
relativeImp/relativeImp.py
relativeImp-0.0.2.dist-info/LICENSE.txt
relativeImp-0.0.2.dist-info/METADATA
relativeImp-0.0.2.dist-info/WHEEL
relativeImp-0.0.2.dist-info/top_level.txt
relativeImp-0.0.2.dist-info/RECORD
