Metadata-Version: 2.1
Name: relativeImp
Version: 0.0.2
Summary: relativeImp is a Python package to conduct the key driver analysis and generate relative importance by driver.
Home-page: UNKNOWN
Author: Dan Yang
Author-email: dyang4@gmail.com
License: LICENSE.txt
Platform: UNKNOWN
Requires-Python: >=3.5
Requires-Dist: pandas
Requires-Dist: numpy
